odoo10_addon_account_multicurrency_revaluation-10.0.2.0.1-py2.7-nspkg.pth
odoo/addons/account_multicurrency_revaluation/README.rst
odoo/addons/account_multicurrency_revaluation/__init__.py
odoo/addons/account_multicurrency_revaluation/__manifest__.py
odoo/addons/account_multicurrency_revaluation/demo/account_demo.xml
odoo/addons/account_multicurrency_revaluation/demo/currency_demo.xml
odoo/addons/account_multicurrency_revaluation/i18n/account_multicurrency_revaluation.pot
odoo/addons/account_multicurrency_revaluation/i18n/am.po
odoo/addons/account_multicurrency_revaluation/i18n/ar.po
odoo/addons/account_multicurrency_revaluation/i18n/bg.po
odoo/addons/account_multicurrency_revaluation/i18n/bs.po
odoo/addons/account_multicurrency_revaluation/i18n/ca.po
odoo/addons/account_multicurrency_revaluation/i18n/ca_ES.po
odoo/addons/account_multicurrency_revaluation/i18n/cs.po
odoo/addons/account_multicurrency_revaluation/i18n/da.po
odoo/addons/account_multicurrency_revaluation/i18n/de.po
odoo/addons/account_multicurrency_revaluation/i18n/el_GR.po
odoo/addons/account_multicurrency_revaluation/i18n/en_AU.po
odoo/addons/account_multicurrency_revaluation/i18n/en_GB.po
odoo/addons/account_multicurrency_revaluation/i18n/es.po
odoo/addons/account_multicurrency_revaluation/i18n/es_AR.po
odoo/addons/account_multicurrency_revaluation/i18n/es_CL.po
odoo/addons/account_multicurrency_revaluation/i18n/es_CO.po
odoo/addons/account_multicurrency_revaluation/i18n/es_CR.po
odoo/addons/account_multicurrency_revaluation/i18n/es_DO.po
odoo/addons/account_multicurrency_revaluation/i18n/es_EC.po
odoo/addons/account_multicurrency_revaluation/i18n/es_ES.po
odoo/addons/account_multicurrency_revaluation/i18n/es_MX.po
odoo/addons/account_multicurrency_revaluation/i18n/es_PE.po
odoo/addons/account_multicurrency_revaluation/i18n/es_PY.po
odoo/addons/account_multicurrency_revaluation/i18n/es_VE.po
odoo/addons/account_multicurrency_revaluation/i18n/et.po
odoo10_addon_account_multicurrency_revaluation-10.0.2.0.1.dist-info/DESCRIPTION.rst
odoo10_addon_account_multicurrency_revaluation-10.0.2.0.1.dist-info/METADATA
odoo10_addon_account_multicurrency_revaluation-10.0.2.0.1.dist-info/RECORD
odoo10_addon_account_multicurrency_revaluation-10.0.2.0.1.dist-info/WHEEL
odoo10_addon_account_multicurrency_revaluation-10.0.2.0.1.dist-info/metadata.json
odoo10_addon_account_multicurrency_revaluation-10.0.2.0.1.dist-info/namespace_packages.txt
odoo10_addon_account_multicurrency_revaluation-10.0.2.0.1.dist-info/top_level.txt
